pemudapersis_bot
