Metadata-Version: 2.1
Name: pemudapersis-bot
Version: 1.2.5
Summary: The official chatbot of Pemuda Persatuan Islam (PERSIS)
Home-page: UNKNOWN
Author: zamzambadruzaman
Author-email: azzambz@pm.me
License: MIT
Platform: UNKNOWN
Requires-Python: >=3.8
